Workbook

Sheet Sales Log
A1: DM TRADE SOLUTIONS LLC — Sales Log 2026
A2: Period: February 15, 2026 — Present
A4: Invoice # | B4: Date | C4: Customer Name | D4: Description | E4: Category | F4: Qty | G4: Unit Price | H4: Total Amount | I4: Payment Method | J4: Payment Date | K4: Delivery Method | L4: Tracking / Notes
H5: =IF(F5<>"",F5*G5,"")
H6: =IF(F6<>"",F6*G6,"")
H7: =IF(F7<>"",F7*G7,"")
H8: =IF(F8<>"",F8*G8,"")
H9: =IF(F9<>"",F9*G9,"")
H10: =IF(F10<>"",F10*G10,"")
H11: =IF(F11<>"",F11*G11,"")
H12: =IF(F12<>"",F12*G12,"")
H13: =IF(F13<>"",F13*G13,"")
H14: =IF(F14<>"",F14*G14,"")
H15: =IF(F15<>"",F15*G15,"")
H16: =IF(F16<>"",F16*G16,"")
... H24: =IF(F24<>"",F24*G24,"")
G25: TOTAL: | H25: =SUM(H5:H24) -> 0

Sheet Summary
A1: Sales Summary
A3: Category | B3: # of Sales | C3: Total Revenue
A4: Equipment Sale | B4: =COUNTIF('Sales Log'!E:E,A4) -> 0 | C4: =SUMIF('Sales Log'!E:E,A4,'Sales Log'!H:H) -> 0
A5: Parts Sale | B5: =COUNTIF('Sales Log'!E:E,A5) -> 0 | C5: =SUMIF('Sales Log'!E:E,A5,'Sales Log'!H:H) -> 0
A6: Equipment Selection | B6: =COUNTIF('Sales Log'!E:E,A6) -> 0 | C6: =SUMIF('Sales Log'!E:E,A6,'Sales Log'!H:H) -> 0
A7: Repair Service | B7: =COUNTIF('Sales Log'!E:E,A7) -> 0 | C7: =SUMIF('Sales Log'!E:E,A7,'Sales Log'!H:H) -> 0
A8: Commissioning | B8: =COUNTIF('Sales Log'!E:E,A8) -> 0 | C8: =SUMIF('Sales Log'!E:E,A8,'Sales Log'!H:H) -> 0
A9: Other | B9: =COUNTIF('Sales Log'!E:E,A9) -> 0 | C9: =SUMIF('Sales Log'!E:E,A9,'Sales Log'!H:H) -> 0
A10: TOTAL | B10: =SUM(B4:B9) -> 0 | C10: =SUM(C4:C9) -> 0
